{
    "namespace":"scoreboard",
    
    "scoreboard_sidebar": {
      "type": "panel",
      "size": [ "100%cm + 100", "100%c + 100" ],
      "anchor_from": "right_middle",
      "anchor_to": "right_middle",
      "controls": [
         {
          "main": {
            "type": "image",
            "texture": "textures/ui/Black",
            "alpha": 0.5,
            "size": [ "100%cm", "100%c + 40" ],
            "controls": [
               {
                  "logo": {
                     "type": "panel",
                     "size": [ "100%cm", "100%c" ],
                     "anchor_from": "top_middle",
                     "anchor_to": "top_middle",
                     "controls": [
                        {
                           "main": {
                              "type": "image",
                              "texture": "textures/ui/sb-title.png",
                              "alpha": 1,
                              "anchor_from":"top_middle",
                              "anchor_to": "top_middle",
                              "size": [ 100, 40 ],
                              "offset": [ 0, -3 ],
                              "layer": 1
                           }
                        }
                     ],
                     "bindings": [
                        {
                           "binding_name": "#objective_sidebar_name",
                           "binding_type": "global"
                        }
                     ]
                  }
              },
              {
                "lists": {
                  "type": "panel",
                  "anchor_from": "buttom_left",
                  "anchor_to": "buttom_left",
                  "inherit_max_sibling_width": true,
                  "offset": [ 0, 17 ],
                  "size": [ "100%c", "100%cm" ],
                  "controls": [
                    {
                      "players": {
                        "type": "stack_panel",
                        "anchor_from": "top_left",
                        "anchor_to": "top_left",
                        "size": [ "100%cm", "100%c" ],
                        "orientation": "vertical",
                        "collection_name": "scoreboard_players",
                        "factory": {
                          "name": "player_list_factory",
                          "control_name": "scoreboard.scoreboard_sidebar_player"
                        },
                        "bindings": [
                          {
                            "binding_name": "#scoreboard_sidebar_size",
                            "binding_type": "global",
                            "binding_name_override": "#collection_length"
                          }
                        ]
                      }
                    }
                  ]
                }
              }
            ]
          }
        }
      ],
      "bindings": [
        {
          "binding_name": "#scoreboard_sidebar_visible",
          "binding_type": "global",
          "binding_name_override": "#visible"
        }
      ]
    }
  }
